<?xml version='1.0' encoding='utf-8'?>
<Episode>
  <directors>
    <item index="0">
      <photo/>
      <role/>
      <name>Kevin Tancharoen</name>
    </item>
  </directors>
  <guest_stars/>
  <originally_available_at>2016-12-06</originally_available_at>
  <producers/>
  <rating>7.6</rating>
  <summary>S.H.I.E.L.D. and Ghost Rider find themselves unlikely allies when the lives of all of Los Angeles hang in the balance.</summary>
  <tags/>
  <thumbs>
    <item external="True" url="https://thetvdb.com/banners/episodes/263365/5821104.jpg" provider="com.plexapp.agents.thetvdb" media="com.plexapp.agents.thetvdb_7d076bef057390575b3f8ab019b6acd2dfde3c55"/>
  </thumbs>
  <title>The Laws of Inferno Dynamics</title>
  <writers>
    <item index="0">
      <photo/>
      <role/>
      <name>Paul Zbyszewski</name>
    </item>
  </writers>
</Episode>
