<VideoStream timebaseNumerator="1" timebaseDenomenator="1000">
<Group pts="0" duration="1681" size="1089980" />
<Group pts="1710" duration="2542" size="1207801" />
<Group pts="4296" duration="1927" size="911349" />
<Group pts="6256" duration="3526" size="788224" />
<Group pts="9843" duration="2665" size="852110" />
<Group pts="12554" duration="4756" size="2365824" />
<Group pts="17392" duration="2378" size="720904" />
<Group pts="19811" duration="2419" size="377444" />
<Group pts="22272" duration="1804" size="435059" />
<Group pts="24107" duration="3608" size="637485" />
<Group pts="27778" duration="1312" size="435315" />
<Group pts="29112" duration="1968" size="582604" />
<Group pts="31114" duration="5043" size="820269" />
<Group pts="36245" duration="1353" size="296590" />
<Group pts="37621" duration="1558" size="355689" />
<Group pts="39206" duration="1148" size="358544" />
<Group pts="40374" duration="1394" size="282745" />
<Group pts="41792" duration="1886" size="726424" />
<Group pts="43710" duration="5248" size="1083052" />
<Group pts="49049" duration="9348" size="1487732" />
<Group pts="58558" duration="3649" size="700567" />
<Group pts="62271" duration="4715" size="1093833" />
<Group pts="67067" duration="8405" size="1107681" />
<Group pts="75617" duration="1558" size="244275" />
<Group pts="77202" duration="7052" size="1224981" />
<Group pts="84376" duration="4387" size="763467" />
<Group pts="88839" duration="4428" size="758346" />
<Group pts="93343" duration="2050" size="415698" />
<Group pts="95429" duration="2091" size="366699" />
<Group pts="97556" duration="3075" size="546835" />
<Group pts="100684" duration="5740" size="793273" />
<Group pts="106523" duration="9102" size="1487147" />
<Group pts="115782" duration="2009" size="355527" />
<Group pts="117826" duration="4674" size="656790" />
<Group pts="122581" duration="2542" size="425445" />
<Group pts="125167" duration="2583" size="325413" />
<Group pts="127794" duration="9102" size="1538538" />
<Group pts="137054" duration="5166" size="707759" />
<Group pts="142309" duration="1558" size="243838" />
<Group pts="143894" duration="8528" size="1387876" />
<Group pts="152569" duration="2337" size="912078" />
<Group pts="154946" duration="1886" size="467168" />
<Group pts="156865" duration="1517" size="350175" />
<Group pts="158408" duration="2788" size="572414" />
<Group pts="161244" duration="3936" size="1027459" />
<Group pts="165248" duration="3075" size="616893" />
<Group pts="168377" duration="4469" size="1395967" />
<Group pts="172923" duration="9430" size="5035620" />
<Group pts="182516" duration="9430" size="4061957" />
<Group pts="192109" duration="3690" size="1355682" />
<Group pts="195862" duration="2706" size="941346" />
<Group pts="198615" duration="1353" size="326855" />
<Group pts="199991" duration="9430" size="3266345" />
<Group pts="209584" duration="4100" size="1314016" />
<Group pts="213755" duration="9430" size="2596045" />
<Group pts="223348" duration="9430" size="2721063" />
<Group pts="232941" duration="1722" size="627289" />
<Group pts="234693" duration="2911" size="526663" />
<Group pts="237654" duration="2091" size="442665" />
<Group pts="239781" duration="2378" size="518341" />
<Group pts="242200" duration="2952" size="591424" />
<Group pts="245203" duration="1066" size="217134" />
<Group pts="246288" duration="5986" size="1227904" />
<Group pts="252377" duration="5494" size="975333" />
<Group pts="257966" duration="3895" size="703901" />
<Group pts="261928" duration="1681" size="256662" />
<Group pts="263638" duration="4674" size="1164507" />
<Group pts="268393" duration="2214" size="401460" />
<Group pts="270645" duration="4059" size="1169435" />
<Group pts="274774" duration="1886" size="457139" />
<Group pts="276693" duration="2993" size="850186" />
<Group pts="279738" duration="4100" size="1260801" />
<Group pts="283909" duration="5781" size="1357324" />
<Group pts="289789" duration="4346" size="847605" />
<Group pts="294211" duration="5863" size="1215036" />
<Group pts="300175" duration="3362" size="672232" />
<Group pts="303595" duration="3526" size="794416" />
<Group pts="307182" duration="1476" size="213273" />
<Group pts="308683" duration="5986" size="1266179" />
<Group pts="314773" duration="943" size="197785" />
<Group pts="315732" duration="9430" size="1797715" />
<Group pts="325325" duration="5289" size="1100246" />
<Group pts="330705" duration="2050" size="323241" />
<Group pts="332791" duration="2419" size="843775" />
<Group pts="335252" duration="3116" size="966981" />
<Group pts="338421" duration="3567" size="1078988" />
<Group pts="342050" duration="1476" size="256028" />
<Group pts="343552" duration="6232" size="2250987" />
<Group pts="349891" duration="4551" size="1602384" />
<Group pts="354521" duration="5822" size="2027203" />
<Group pts="360443" duration="2624" size="725968" />
<Group pts="363113" duration="1968" size="556283" />
<Group pts="365115" duration="2460" size="429505" />
<Group pts="367617" duration="1968" size="559397" />
<Group pts="369619" duration="1189" size="286488" />
<Group pts="370829" duration="1722" size="517174" />
<Group pts="372581" duration="1435" size="259572" />
<Group pts="374040" duration="5166" size="1546309" />
<Group pts="379296" duration="1927" size="467332" />
<Group pts="381256" duration="1599" size="326497" />
<Group pts="382882" duration="1968" size="415005" />
<Group pts="384884" duration="1517" size="509703" />
<Group pts="386428" duration="5166" size="1975498" />
<Group pts="391683" duration="2829" size="710197" />
<Group pts="394561" duration="3198" size="988154" />
<Group pts="397814" duration="2132" size="487682" />
<Group pts="399983" duration="943" size="516746" />
<Group pts="400942" duration="9430" size="2311330" />
<Group pts="410535" duration="5535" size="1389193" />
<Group pts="416166" duration="2747" size="1477587" />
<Group pts="418960" duration="1968" size="2519146" />
<Group pts="420962" duration="3772" size="1792739" />
<Group pts="424799" duration="5125" size="3526403" />
<Group pts="430013" duration="5207" size="1509981" />
<Group pts="435310" duration="2132" size="1314826" />
<Group pts="437479" duration="9430" size="4927689" />
<Group pts="447072" duration="1845" size="954966" />
<Group pts="448948" duration="5166" size="1670940" />
<Group pts="454204" duration="1476" size="679905" />
<Group pts="455705" duration="8241" size="4800391" />
<Group pts="464089" duration="3936" size="1680824" />
<Group pts="468093" duration="9430" size="5062252" />
<Group pts="477686" duration="6724" size="1895679" />
<Group pts="484526" duration="3362" size="647137" />
<Group pts="487946" duration="6765" size="1423551" />
<Group pts="494828" duration="3485" size="816334" />
<Group pts="498373" duration="8528" size="2105618" />
<Group pts="507048" duration="9430" size="1837547" />
<Group pts="516641" duration="5986" size="2276647" />
<Group pts="522731" duration="3321" size="1122569" />
<Group pts="526109" duration="2378" size="867158" />
<Group pts="528528" duration="1722" size="386786" />
<Group pts="530280" duration="1763" size="692662" />
<Group pts="532073" duration="2214" size="470694" />
<Group pts="534325" duration="2542" size="821697" />
<Group pts="536911" duration="984" size="179107" />
<Group pts="537912" duration="9307" size="4262893" />
<Group pts="547380" duration="4961" size="3183455" />
<Group pts="552427" duration="3936" size="1290781" />
<Group pts="556431" duration="2870" size="543504" />
<Group pts="559350" duration="5576" size="4750897" />
<Group pts="565023" duration="2337" size="1801875" />
<Group pts="567400" duration="4223" size="971635" />
<Group pts="571696" duration="1558" size="350436" />
<Group pts="573281" duration="4182" size="1049229" />
<Group pts="577535" duration="6601" size="1669804" />
<Group pts="584250" duration="3280" size="906179" />
<Group pts="587587" duration="5330" size="2503404" />
<Group pts="593009" duration="2419" size="853256" />
<Group pts="595470" duration="4592" size="1094565" />
<Group pts="600141" duration="9430" size="5031038" />
<Group pts="609734" duration="6355" size="3232210" />
<Group pts="616199" duration="7954" size="3735209" />
<Group pts="624290" duration="9430" size="7170287" />
<Group pts="633883" duration="9430" size="5343694" />
<Group pts="643476" duration="9430" size="2798197" />
<Group pts="653069" duration="3608" size="857894" />
<Group pts="656739" duration="7913" size="1982501" />
<Group pts="664789" duration="3321" size="694980" />
<Group pts="668167" duration="3813" size="720080" />
<Group pts="672046" duration="2501" size="574202" />
<Group pts="674591" duration="1558" size="382872" />
<Group pts="676175" duration="3403" size="787269" />
<Group pts="679637" duration="3854" size="999534" />
<Group pts="683558" duration="1886" size="678884" />
<Group pts="685476" duration="4264" size="2034007" />
<Group pts="689814" duration="2337" size="540051" />
<Group pts="692191" duration="2337" size="733028" />
<Group pts="694569" duration="2050" size="482939" />
<Group pts="696654" duration="2829" size="1274321" />
<Group pts="699532" duration="1271" size="517570" />
<Group pts="700825" duration="2296" size="1736214" />
<Group pts="703161" duration="1968" size="644356" />
<Group pts="705163" duration="1927" size="562041" />
<Group pts="707123" duration="5166" size="972798" />
<Group pts="712378" duration="1763" size="520857" />
<Group pts="714172" duration="3362" size="1322219" />
<Group pts="717592" duration="7831" size="1139624" />
<Group pts="725558" duration="4633" size="1386527" />
<Group pts="730271" duration="1722" size="373439" />
<Group pts="732023" duration="3526" size="1013421" />
<Group pts="735610" duration="1640" size="362759" />
<Group pts="737278" duration="4223" size="1084851" />
<Group pts="741574" duration="2337" size="516029" />
<Group pts="743952" duration="2788" size="466318" />
<Group pts="746788" duration="2173" size="426006" />
<Group pts="748998" duration="3690" size="616815" />
<Group pts="752752" duration="1148" size="244098" />
<Group pts="753920" duration="1599" size="439389" />
<Group pts="755546" duration="3157" size="880899" />
<Group pts="758758" duration="4797" size="1999980" />
<Group pts="763638" duration="2419" size="1374349" />
<Group pts="766099" duration="2993" size="787275" />
<Group pts="769143" duration="3362" size="776423" />
<Group pts="772563" duration="5781" size="1867719" />
<Group pts="778444" duration="2460" size="981912" />
<Group pts="780947" duration="2624" size="828393" />
<Group pts="783616" duration="3567" size="747420" />
<Group pts="787245" duration="2665" size="1744326" />
<Group pts="789956" duration="1476" size="176489" />
<Group pts="791457" duration="1722" size="731139" />
<Group pts="793209" duration="984" size="565902" />
<Group pts="794210" duration="3608" size="527624" />
<Group pts="797880" duration="2993" size="432215" />
<Group pts="800925" duration="5658" size="1235580" />
<Group pts="806681" duration="1476" size="518335" />
<Group pts="808182" duration="2050" size="920625" />
<Group pts="810268" duration="2255" size="766717" />
<Group pts="812562" duration="2706" size="844870" />
<Group pts="815314" duration="2665" size="1061445" />
<Group pts="818026" duration="1927" size="879036" />
<Group pts="819986" duration="3608" size="1866515" />
<Group pts="823656" duration="3280" size="1908732" />
<Group pts="826993" duration="8405" size="2408337" />
<Group pts="835543" duration="2747" size="740892" />
<Group pts="838337" duration="3485" size="953242" />
<Group pts="841883" duration="3116" size="779365" />
<Group pts="845053" duration="3075" size="855284" />
<Group pts="848181" duration="2337" size="590488" />
<Group pts="850558" duration="1722" size="451313" />
<Group pts="852310" duration="1722" size="453006" />
<Group pts="854062" duration="3526" size="1433327" />
<Group pts="857648" duration="3813" size="1629939" />
<Group pts="861527" duration="1763" size="455491" />
<Group pts="863321" duration="943" size="272929" />
<Group pts="864280" duration="5576" size="1423110" />
<Group pts="869952" duration="2419" size="935648" />
<Group pts="872413" duration="1394" size="386605" />
<Group pts="873831" duration="1353" size="333446" />
<Group pts="875208" duration="4182" size="1088342" />
<Group pts="879462" duration="1804" size="451994" />
<Group pts="881297" duration="1927" size="429470" />
<Group pts="883257" duration="4633" size="1162264" />
<Group pts="887970" duration="2173" size="697245" />
<Group pts="890181" duration="4428" size="2084942" />
<Group pts="894685" duration="1435" size="637654" />
<Group pts="896145" duration="1271" size="759275" />
<Group pts="897438" duration="3075" size="1541037" />
<Group pts="900566" duration="6191" size="3193117" />
<Group pts="906864" duration="4797" size="1422866" />
<Group pts="911744" duration="1804" size="518957" />
<Group pts="913579" duration="2911" size="932158" />
<Group pts="916541" duration="2214" size="464185" />
<Group pts="918793" duration="3526" size="1105020" />
<Group pts="922380" duration="2542" size="823988" />
<Group pts="924966" duration="7298" size="2290397" />
<Group pts="932390" duration="2132" size="480329" />
<Group pts="934559" duration="984" size="229841" />
<Group pts="935560" duration="4223" size="707268" />
<Group pts="939856" duration="3034" size="813011" />
<Group pts="942942" duration="5740" size="1973607" />
<Group pts="948781" duration="9430" size="2620153" />
<Group pts="958374" duration="3321" size="1030944" />
<Group pts="961752" duration="3649" size="979812" />
<Group pts="965464" duration="3936" size="1007033" />
<Group pts="969468" duration="3567" size="897310" />
<Group pts="973097" duration="2993" size="753754" />
<Group pts="976142" duration="6683" size="1567538" />
<Group pts="982940" duration="2706" size="635247" />
<Group pts="985693" duration="5494" size="1574238" />
<Group pts="991282" duration="6560" size="2005259" />
<Group pts="997955" duration="8077" size="1808402" />
<Group pts="1006172" duration="3034" size="641874" />
<Group pts="1009258" duration="1435" size="243527" />
<Group pts="1010718" duration="2009" size="437664" />
<Group pts="1012762" duration="8774" size="2527704" />
<Group pts="1021687" duration="8118" size="1410436" />
<Group pts="1029946" duration="3977" size="1257348" />
<Group pts="1033991" duration="1763" size="390907" />
<Group pts="1035785" duration="3649" size="1924449" />
<Group pts="1039497" duration="6601" size="1870208" />
<Group pts="1046212" duration="3116" size="1016295" />
<Group pts="1049382" duration="2706" size="666315" />
<Group pts="1052134" duration="4059" size="1299603" />
<Group pts="1056264" duration="1435" size="575540" />
<Group pts="1057723" duration="6560" size="1461496" />
<Group pts="1064397" duration="4182" size="1510105" />
<Group pts="1068651" duration="2993" size="947487" />
<Group pts="1071696" duration="3444" size="868264" />
<Group pts="1075199" duration="2050" size="692670" />
<Group pts="1077285" duration="6109" size="1666005" />
<Group pts="1083499" duration="4879" size="1080367" />
<Group pts="1088462" duration="9184" size="1970842" />
<Group pts="1097805" duration="9225" size="1815825" />
<Group pts="1107189" duration="7011" size="1370921" />
<Group pts="1114322" duration="5904" size="1038828" />
<Group pts="1120328" duration="8651" size="1875579" />
<Group pts="1129128" duration="1722" size="396405" />
<Group pts="1130880" duration="9430" size="3139495" />
<Group pts="1140473" duration="6929" size="2500475" />
<Group pts="1147521" duration="9430" size="3013157" />
<Group pts="1157114" duration="9430" size="2710097" />
<Group pts="1166707" duration="9430" size="1894920" />
<Group pts="1176300" duration="2952" size="564448" />
<Group pts="1179303" duration="3526" size="611267" />
<Group pts="1182890" duration="3157" size="532565" />
<Group pts="1186102" duration="9430" size="3447747" />
<Group pts="1195694" duration="9430" size="4152391" />
<Group pts="1205287" duration="3690" size="1674176" />
<Group pts="1209041" duration="1558" size="388580" />
<Group pts="1210626" duration="5781" size="2043889" />
<Group pts="1216507" duration="943" size="578167" />
<Group pts="1217466" duration="5494" size="2001114" />
<Group pts="1223055" duration="1640" size="824622" />
<Group pts="1224723" duration="9102" size="3015545" />
<Group pts="1233983" duration="9430" size="3850229" />
<Group pts="1243576" duration="6191" size="2809381" />
<Group pts="1249874" duration="6929" size="1291564" />
<Group pts="1256922" duration="5781" size="1408751" />
<Group pts="1262803" duration="943" size="370847" />
<Group pts="1263762" duration="4141" size="719981" />
<Group pts="1267975" duration="3485" size="832710" />
<Group pts="1271520" duration="3895" size="1255264" />
<Group pts="1275483" duration="1886" size="324280" />
<Group pts="1277401" duration="5125" size="826706" />
<Group pts="1282615" duration="2829" size="543741" />
<Group pts="1285493" duration="6765" size="1053899" />
<Group pts="1292374" duration="7052" size="1533615" />
<Group pts="1299548" duration="4510" size="821135" />
<Group pts="1304136" duration="4469" size="707125" />
<Group pts="1308682" duration="5740" size="926785" />
<Group pts="1314521" duration="5207" size="1231969" />
<Group pts="1319818" duration="3567" size="682648" />
<Group pts="1323447" duration="6232" size="1516012" />
<Group pts="1329787" duration="3772" size="571037" />
<Group pts="1333624" duration="5699" size="1417785" />
<Group pts="1339421" duration="6355" size="864338" />
<Group pts="1345886" duration="5904" size="1939410" />
<Group pts="1351892" duration="5002" size="704913" />
<Group pts="1356981" duration="5699" size="1918216" />
<Group pts="1362778" duration="5699" size="1007495" />
<Group pts="1368575" duration="6929" size="1142059" />
<Group pts="1375624" duration="2829" size="773431" />
<Group pts="1378502" duration="3813" size="695240" />
<Group pts="1382381" duration="7216" size="1308598" />
<Group pts="1389722" duration="6970" size="1436637" />
<Group pts="1396812" duration="8077" size="1395850" />
<Group pts="1405029" duration="4346" size="801592" />
<Group pts="1409450" duration="1107" size="274002" />
<Group pts="1410576" duration="4018" size="1099726" />
<Group pts="1414663" duration="7503" size="1284579" />
<Group pts="1422296" duration="8733" size="819168" />
<Group pts="1431180" duration="9430" size="1625460" />
<Group pts="1440773" duration="9430" size="1776923" />
<Group pts="1450366" duration="7421" size="1174907" />
<Group pts="1457915" duration="5002" size="1044123" />
<Group pts="1463003" duration="6724" size="1660422" />
<Group pts="1469843" duration="9430" size="2407905" />
<Group pts="1479436" duration="2255" size="496434" />
<Group pts="1481730" duration="3936" size="524659" />
<Group pts="1485734" duration="5043" size="1287262" />
<Group pts="1490864" duration="3485" size="1220364" />
<Group pts="1494410" duration="1025" size="224117" />
<Group pts="1495452" duration="8979" size="3046302" />
<Group pts="1504586" duration="7544" size="1568579" />
<Group pts="1512261" duration="3649" size="791594" />
<Group pts="1515973" duration="2460" size="819486" />
<Group pts="1518475" duration="3444" size="737294" />
<Group pts="1521979" duration="1804" size="567332" />
<Group pts="1523814" duration="3116" size="584972" />
<Group pts="1526984" duration="8979" size="1453782" />
<Group pts="1536118" duration="5166" size="871849" />
<Group pts="1541373" duration="9430" size="3652612" />
<Group pts="1550966" duration="5248" size="1112987" />
<Group pts="1556305" duration="9430" size="2654220" />
<Group pts="1565898" duration="9430" size="2991129" />
<Group pts="1575491" duration="6355" size="2448448" />
<Group pts="1581955" duration="6724" size="1777519" />
<Group pts="1588795" duration="7462" size="1236641" />
<Group pts="1596386" duration="7995" size="1828042" />
<Group pts="1604520" duration="6109" size="1099222" />
<Group pts="1610734" duration="6232" size="1553487" />
<Group pts="1617074" duration="9430" size="1889505" />
<Group pts="1626667" duration="3977" size="775843" />
<Group pts="1630712" duration="4633" size="807413" />
<Group pts="1635425" duration="9102" size="1868268" />
<Group pts="1644685" duration="5207" size="1060785" />
<Group pts="1649982" duration="8446" size="1322966" />
<Group pts="1658574" duration="6601" size="1479369" />
<Group pts="1665289" duration="5822" size="1421610" />
<Group pts="1671211" duration="2542" size="550745" />
<Group pts="1673797" duration="6683" size="1490512" />
<Group pts="1680596" duration="2091" size="369835" />
<Group pts="1682723" duration="9430" size="4809817" />
<Group pts="1692316" duration="3526" size="1382903" />
<Group pts="1695902" duration="1845" size="681582" />
<Group pts="1697779" duration="3895" size="1039002" />
<Group pts="1701742" duration="2788" size="1035695" />
<Group pts="1704578" duration="8036" size="2196966" />
<Group pts="1712753" duration="5330" size="1055845" />
<Group pts="1718175" duration="9430" size="2167919" />
<Group pts="1727768" duration="3075" size="636334" />
<Group pts="1730896" duration="5248" size="1703954" />
<Group pts="1736234" duration="3239" size="1640648" />
<Group pts="1739529" duration="5248" size="1812924" />
<Group pts="1744868" duration="9430" size="2237967" />
<Group pts="1754461" duration="4838" size="822574" />
<Group pts="1759383" duration="4633" size="794073" />
<Group pts="1764096" duration="5043" size="1079232" />
<Group pts="1769226" duration="4674" size="1151996" />
<Group pts="1773980" duration="6519" size="1264778" />
<Group pts="1780612" duration="9430" size="1869402" />
<Group pts="1790205" duration="3936" size="726468" />
<Group pts="1794209" duration="5371" size="1088649" />
<Group pts="1799673" duration="7421" size="1521121" />
<Group pts="1807222" duration="5617" size="1098027" />
<Group pts="1812936" duration="4100" size="828393" />
<Group pts="1817107" duration="3690" size="813908" />
<Group pts="1820861" duration="7257" size="1457567" />
<Group pts="1828243" duration="1435" size="549092" />
<Group pts="1829703" duration="3321" size="1213963" />
<Group pts="1833081" duration="1312" size="379327" />
<Group pts="1834416" duration="2542" size="976751" />
<Group pts="1837002" duration="1148" size="530229" />
<Group pts="1838170" duration="7585" size="3708974" />
<Group pts="1845886" duration="1640" size="600498" />
<Group pts="1847554" duration="4223" size="1234220" />
<Group pts="1851850" duration="4633" size="1443641" />
<Group pts="1856563" duration="3690" size="1087587" />
<Group pts="1860317" duration="6355" size="2086493" />
<Group pts="1866782" duration="2132" size="722792" />
<Group pts="1868950" duration="6888" size="1354787" />
<Group pts="1875957" duration="9430" size="1863782" />
<Group pts="1885550" duration="7011" size="1610185" />
<Group pts="1892682" duration="8856" size="1689347" />
<Group pts="1901691" duration="5535" size="1071461" />
<Group pts="1907322" duration="8036" size="1860837" />
<Group pts="1915497" duration="4879" size="869783" />
<Group pts="1920460" duration="2952" size="441059" />
<Group pts="1923463" duration="2337" size="1058637" />
<Group pts="1925840" duration="1927" size="730258" />
<Group pts="1927801" duration="1640" size="507158" />
<Group pts="1929469" duration="4264" size="2509310" />
<Group pts="1933807" duration="1927" size="583233" />
<Group pts="1935767" duration="6109" size="1769199" />
<Group pts="1941981" duration="1886" size="610997" />
<Group pts="1943900" duration="1066" size="275256" />
<Group pts="1944984" duration="6396" size="2209127" />
<Group pts="1951491" duration="7339" size="2015491" />
<Group pts="1958957" duration="8241" size="3956214" />
<Group pts="1967340" duration="3608" size="1239839" />
<Group pts="1971010" duration="3444" size="904802" />
<Group pts="1974514" duration="2624" size="530602" />
<Group pts="1977183" duration="4305" size="1800374" />
<Group pts="1981563" duration="5576" size="1242312" />
<Group pts="1987235" duration="8118" size="1622298" />
<Group pts="1995493" duration="6888" size="1089958" />
<Group pts="2002500" duration="8733" size="1342706" />
<Group pts="2011384" duration="5576" size="2247113" />
<Group pts="2017056" duration="2050" size="899394" />
<Group pts="2019142" duration="2419" size="649814" />
<Group pts="2021603" duration="3895" size="1125788" />
<Group pts="2025565" duration="2993" size="754135" />
<Group pts="2028610" duration="2460" size="931012" />
<Group pts="2031112" duration="2829" size="1640094" />
<Group pts="2033990" duration="3034" size="906217" />
<Group pts="2037076" duration="2665" size="1039429" />
<Group pts="2039788" duration="6109" size="1937229" />
<Group pts="2046002" duration="3936" size="1169492" />
<Group pts="2050006" duration="2255" size="723138" />
<Group pts="2052300" duration="2870" size="920344" />
<Group pts="2055220" duration="5740" size="1533848" />
<Group pts="2061059" duration="4756" size="1746805" />
<Group pts="2065897" duration="3895" size="1893966" />
<Group pts="2069859" duration="2009" size="588716" />
<Group pts="2071903" duration="4059" size="1183963" />
<Group pts="2076032" duration="2255" size="687586" />
<Group pts="2078326" duration="2214" size="783081" />
<Group pts="2080578" duration="1886" size="1476273" />
<Group pts="2082497" duration="1107" size="1029290" />
<Group pts="2083623" duration="1189" size="924416" />
<Group pts="2084833" duration="1517" size="1068955" />
<Group pts="2086376" duration="902" size="770791" />
<Group pts="2087293" duration="1517" size="988671" />
<Group pts="2088837" duration="1353" size="666862" />
<Group pts="2090213" duration="2009" size="2353458" />
<Group pts="2092257" duration="1558" size="1193703" />
<Group pts="2093842" duration="1558" size="940931" />
<Group pts="2095426" duration="1435" size="1708525" />
<Group pts="2096886" duration="1722" size="1365622" />
<Group pts="2098638" duration="3485" size="1150291" />
<Group pts="2102183" duration="1558" size="500551" />
<Group pts="2103768" duration="1066" size="545831" />
<Group pts="2104853" duration="1271" size="889324" />
<Group pts="2106145" duration="1189" size="251007" />
<Group pts="2107355" duration="3362" size="1884086" />
<Group pts="2110775" duration="4961" size="1517156" />
<Group pts="2115822" duration="9430" size="1502536" />
<Group pts="2125415" duration="8200" size="1698564" />
<Group pts="2133756" duration="1968" size="509991" />
<Group pts="2135758" duration="8118" size="1259761" />
<Group pts="2144017" duration="2050" size="318915" />
<Group pts="2146102" duration="5699" size="954527" />
<Group pts="2151900" duration="4674" size="600534" />
<Group pts="2156654" duration="5330" size="1201768" />
<Group pts="2162076" duration="7954" size="1242673" />
<Group pts="2170168" duration="4920" size="899614" />
<Group pts="2175173" duration="4346" size="710575" />
<Group pts="2179594" duration="5576" size="799880" />
<Group pts="2185266" duration="7421" size="2769759" />
<Group pts="2192815" duration="9430" size="2029421" />
<Group pts="2202408" duration="6724" size="1596637" />
<Group pts="2209248" duration="3034" size="622692" />
<Group pts="2212335" duration="4264" size="1017127" />
<Group pts="2216673" duration="5945" size="1604199" />
<Group pts="2222720" duration="3485" size="613555" />
<Group pts="2226265" duration="6724" size="1552196" />
<Group pts="2233106" duration="8610" size="2094877" />
<Group pts="2241864" duration="6437" size="1472419" />
<Group pts="2248413" duration="4756" size="1391801" />
<Group pts="2253251" duration="3854" size="974952" />
<Group pts="2257171" duration="3936" size="941372" />
<Group pts="2261175" duration="5535" size="1023490" />
<Group pts="2266806" duration="9430" size="2239145" />
<Group pts="2276399" duration="3649" size="834330" />
<Group pts="2280111" duration="2009" size="394238" />
<Group pts="2282155" duration="8077" size="1301601" />
<Group pts="2290371" duration="2993" size="716632" />
<Group pts="2293416" duration="2829" size="545115" />
<Group pts="2296294" duration="6683" size="1649972" />
<Group pts="2303092" duration="4920" size="1113529" />
<Group pts="2308097" duration="3362" size="508388" />
<Group pts="2311517" duration="9430" size="2110810" />
<Group pts="2321110" duration="7421" size="1259333" />
<Group pts="2328659" duration="4674" size="1077602" />
<Group pts="2333414" duration="3854" size="1329074" />
<Group pts="2337335" duration="2173" size="702760" />
<Group pts="2339545" duration="1189" size="344452" />
<Group pts="2340755" duration="2255" size="503358" />
<Group pts="2343049" duration="2009" size="603009" />
<Group pts="2345093" duration="3567" size="1373357" />
<Group pts="2348721" duration="1148" size="240473" />
<Group pts="2349889" duration="3485" size="930512" />
<Group pts="2353434" duration="1927" size="385340" />
<Group pts="2355394" duration="2460" size="592677" />
<Group pts="2357897" duration="3157" size="592341" />
<Group pts="2361109" duration="7626" size="1400759" />
<Group pts="2368866" duration="1845" size="438202" />
<Group pts="2370743" duration="3731" size="740164" />
<Group pts="2374539" duration="1148" size="295917" />
<Group pts="2375706" duration="1558" size="542907" />
<Group pts="2377291" duration="984" size="169677" />
<Group pts="2378292" duration="5781" size="2137043" />
<Group pts="2384173" duration="2214" size="733406" />
<Group pts="2386425" duration="6068" size="1233607" />
<Group pts="2392598" duration="5412" size="1713264" />
<Group pts="2398104" duration="4838" size="919386" />
<Group pts="2403025" duration="5412" size="1652458" />
<Group pts="2408531" duration="8077" size="2312196" />
<Group pts="2416747" duration="9430" size="2671095" />
<Group pts="2426340" duration="4305" size="1428577" />
<Group pts="2430720" duration="4510" size="1231218" />
<Group pts="2435308" duration="9430" size="2749614" />
<Group pts="2444901" duration="5904" size="1457008" />
<Group pts="2450907" duration="1886" size="1185276" />
<Group pts="2452825" duration="2091" size="711657" />
<Group pts="2454952" duration="6765" size="1727047" />
<Group pts="2461834" duration="6396" size="1790847" />
<Group pts="2468341" duration="3526" size="873283" />
<Group pts="2471928" duration="6150" size="1622957" />
<Group pts="2478184" duration="6519" size="1389697" />
<Group pts="2484815" duration="3977" size="1209413" />
<Group pts="2488861" duration="5494" size="1206483" />
<Group pts="2494450" duration="4961" size="1414786" />
<Group pts="2499497" duration="5535" size="1078671" />
<Group pts="2505127" duration="2378" size="627531" />
<Group pts="2507546" duration="9430" size="2193184" />
<Group pts="2517139" duration="3608" size="823820" />
<Group pts="2520810" duration="2378" size="805899" />
<Group pts="2523229" duration="2993" size="799059" />
<Group pts="2526274" duration="7380" size="2719440" />
<Group pts="2533781" duration="4346" size="1052513" />
<Group pts="2538202" duration="3280" size="1060753" />
<Group pts="2541539" duration="1640" size="403553" />
<Group pts="2543207" duration="8446" size="2414290" />
<Group pts="2551799" duration="2132" size="401776" />
<Group pts="2553968" duration="3854" size="1440406" />
<Group pts="2557888" duration="369" size="11038" />
</VideoStream>
