<?xml version='1.0' encoding='utf-8'?>
<Episode>
  <directors>
    <item index="0">
      <photo/>
      <role/>
      <name>Jeff Woolnough</name>
    </item>
  </directors>
  <guest_stars/>
  <originally_available_at>2017-02-08</originally_available_at>
  <producers/>
  <rating>7.8</rating>
  <summary>Holden and Miller butt heads about how the raid was handled.</summary>
  <tags/>
  <thumbs>
    <item external="True" url="https://thetvdb.com/banners/episodes/280619/5684770.jpg" provider="com.plexapp.agents.thetvdb" media="com.plexapp.agents.thetvdb_afd54cd8670f3671005ca1252ee35944ecd4fd67"/>
  </thumbs>
  <title>Static</title>
  <writers>
    <item index="0">
      <photo/>
      <role/>
      <name>Robin Veith</name>
    </item>
  </writers>
</Episode>
